<dir><title>[B][COLOR white]Hành Động - Action[/COLOR][/B]</title><tmdb>genre/movies/28</tmdb></dir>
<dir><title>[B][COLOR white]Phiêu Lưu - Adventure[/COLOR][/B]</title><tmdb>genre/movies/12</tmdb></dir>
<dir><title>[B][COLOR white]Hoạt Hinh - Animated[/COLOR][/B]</title><tmdb>genre/movies/16</tmdb></dir>
<dir><title>[B][COLOR white]Hài Hước - Comedy[/COLOR][/B]</title><tmdb>genre/movies/35</tmdb></dir>
<dir><title>[B][COLOR white]Tài Liệu - Documentary[/COLOR][/B]</title><tmdb>genre/movies/99</tmdb></dir>
<dir><title>[B][COLOR white]Kịch - Drama[/COLOR][/B]</title><tmdb>genre/movies/18</tmdb></dir>
<dir><title>[B][COLOR white]Gia Đình -  Family[/COLOR][/B]</title><tmdb>genre/movies/10751</tmdb></dir>
<dir><title>[B][COLOR white]Ảo -  Fantasy[/COLOR][/B]</title><tmdb>genre/movies/14</tmdb></dir>
<dir><title>[B][COLOR white]Lịch Sữ - History[/COLOR][/B]</title><tmdb>genre/movies/36</tmdb></dir>
<dir><title>[B][COLOR white]Kinh Dị - Horror[/COLOR][/B]</title><tmdb>genre/movies/27</tmdb></dir>
<dir><title>[B][COLOR white]Nhạc - Music[/COLOR][/B]</title><tmdb>genre/movies/10402</tmdb></dir>
<dir><title>[B][COLOR white]Huyền Bí - Mystery[/COLOR][/B]</title><tmdb>genre/movies/9648</tmdb></dir>
<dir><title>[B][COLOR white]Lãng Mạn - Romance[/COLOR][/B]</title><tmdb>genre/movies/10749</tmdb></dir>
<dir><title>[B][COLOR white]Khoa Học Viễn Tưỡng - Sci-Fi[/COLOR][/B]</title><tmdb>genre/movies/878</tmdb></dir>
<dir><title>[B][COLOR white]Giết Người - Thriller[/COLOR][/B]</title><tmdb>genre/movies/53</tmdb></dir>
<dir><title>[B][COLOR white]Chiến Tranh - War[/COLOR][/B]</title><tmdb>genre/movies/10752</tmdb></dir>
<dir><title>[B][COLOR white]Cowboy - Western[/COLOR][/B]</title><tmdb>genre/movies/37</tmdb></dir>
